ipernity/__init__.py
ipernity/__main__.py
ipernity/_version.py
ipernity/api.py
ipernity/auth.py
ipernity/exceptions.py
ipernity/method.py
ipernity/methods.json
PyIpernity-0.3.1.dist-info/LICENSE
PyIpernity-0.3.1.dist-info/METADATA
PyIpernity-0.3.1.dist-info/WHEEL
PyIpernity-0.3.1.dist-info/top_level.txt
PyIpernity-0.3.1.dist-info/RECORD
