Metadata-Version: 2.1
Name: PyIpernity
Version: 0.3.1
Summary: Library to access the Ipernity API
Author-email: rcw-2 <mail@rcw-2.de>
Project-URL: Documentation, https://pyipernity.readthedocs.io/
Project-URL: Homepage, https://github.com/rcw-2/python-ipernity
Keywords: ipernity
Classifier: Development Status :: 3 - Alpha
Classifier: Intended Audience :: Developers
Classifier: License :: OSI Approved :: MIT License
Classifier: Programming Language :: Python :: 3
Classifier: Topic :: Multimedia :: Graphics
Classifier: Topic :: Software Development :: Libraries :: Python Modules
Requires-Python: >=3.8
License-File: LICENSE
Requires-Dist: requests
Provides-Extra: docs
Requires-Dist: sphinx ; extra == 'docs'
Requires-Dist: tomli ; (python_version < "3.11") and extra == 'docs'
Provides-Extra: test
Requires-Dist: PyYAML ; extra == 'test'
Requires-Dist: pytest ; extra == 'test'
Requires-Dist: pytest-cov ; extra == 'test'
